{"name":"cutiefly","types":["bug","fairy"],"index":742,"abilities":[{"ability":{"name":"honey-gather","descriprion":"The Pokémon may gather Honey after a battle.","index":118,"generation":"iv"},"hidden":false},{"ability":{"name":"shield-dust","descriprion":"This Pokémon’s dust blocks the additional effects of\nattacks taken.","index":19,"generation":"iii"},"hidden":false},{"ability":{"name":"sweet-veil","descriprion":"Prevents itself and ally Pokémon from falling asleep.","index":175,"generation":"vi"},"hidden":true}],"gender_ratio":{"male":50,"female":50},"base_stats":{"hp":40,"attack":45,"defense":40,"special_attack":55,"special_defense":40,"speed":84},"data":{"catch_rate":190,"weight":2,"height":1,"pokedex_color":"yellow","is_legendary":false,"is_mythic":false},"evolution_chain":[{"base_form":"cutiefly","first_evolution":{"name":"ribombee","mode":{"type":"level-up","level":25,"gender":null,"trade":false,"happiness":null,"affection":null,"needs_rain":false,"beauty":null,"time":""}},"second_evolution":null}],"generation":"vii","learned_moves":[{"name":"absorb","level":1,"TM":false},{"name":"stun-spore","level":7,"TM":false},{"name":"toxic","level":0,"TM":true},{"name":"psychic","level":0,"TM":true},{"name":"double-team","level":0,"TM":true},{"name":"light-screen","level":0,"TM":true},{"name":"reflect","level":0,"TM":true},{"name":"swift","level":0,"TM":true},{"name":"dream-eater","level":0,"TM":true},{"name":"leech-life","level":0,"TM":true},{"name":"rest","level":0,"TM":true},{"name":"substitute","level":0,"TM":true},{"name":"thief","level":0,"TM":true},{"name":"snore","level":0,"TM":false},{"name":"protect","level":0,"TM":true},{"name":"endure","level":0,"TM":true},{"name":"charm","level":0,"TM":true},{"name":"swagger","level":0,"TM":true},{"name":"attract","level":0,"TM":true},{"name":"sleep-talk","level":0,"TM":true},{"name":"return","level":0,"TM":true},{"name":"frustration","level":0,"TM":true},{"name":"safeguard","level":0,"TM":true},{"name":"baton-pass","level":0,"TM":false},{"name":"sweet-scent","level":21,"TM":false},{"name":"hidden-power","level":0,"TM":true},{"name":"sunny-day","level":0,"TM":true},{"name":"psych-up","level":0,"TM":true},{"name":"facade","level":0,"TM":true},{"name":"helping-hand","level":0,"TM":false},{"name":"trick","level":0,"TM":false},{"name":"skill-swap","level":0,"TM":false},{"name":"imprison","level":0,"TM":true},{"name":"aromatherapy","level":36,"TM":false},{"name":"fake-tears","level":0,"TM":true},{"name":"silver-wind","level":13,"TM":false},{"name":"signal-beam","level":0,"TM":false},{"name":"aerial-ace","level":0,"TM":true},{"name":"covet","level":0,"TM":false},{"name":"calm-mind","level":0,"TM":true},{"name":"roost","level":0,"TM":true},{"name":"tailwind","level":0,"TM":false},{"name":"u-turn","level":0,"TM":true},{"name":"last-resort","level":0,"TM":false},{"name":"bug-buzz","level":26,"TM":false},{"name":"energy-ball","level":0,"TM":true},{"name":"switcheroo","level":36,"TM":false},{"name":"defog","level":0,"TM":false},{"name":"bug-bite","level":0,"TM":false},{"name":"wonder-room","level":0,"TM":false},{"name":"telekinesis","level":0,"TM":false},{"name":"magic-room","level":0,"TM":false},{"name":"quiver-dance","level":41,"TM":false},{"name":"after-you","level":0,"TM":false},{"name":"round","level":0,"TM":true},{"name":"ally-switch","level":0,"TM":false},{"name":"acrobatics","level":0,"TM":true},{"name":"bestow","level":0,"TM":false},{"name":"struggle-bug","level":10,"TM":false},{"name":"sticky-web","level":0,"TM":false},{"name":"draining-kiss","level":16,"TM":false},{"name":"play-rough","level":0,"TM":true},{"name":"fairy-wind","level":4,"TM":false},{"name":"moonblast","level":0,"TM":false},{"name":"confide","level":0,"TM":true},{"name":"aromatic-mist","level":0,"TM":false},{"name":"powder","level":0,"TM":false},{"name":"dazzling-gleam","level":31,"TM":false},{"name":"infestation","level":0,"TM":true},{"name":"speed-swap","level":0,"TM":false},{"name":"dual-wingbeat","level":0,"TM":false}],"sprite":"https://raw.githubusercontent.com/PokeAPI/sprites/master/sprites/pokemon/742.png"}