{"name":"necrozma","types":["psychic"],"index":800,"abilities":[{"ability":{"name":"prism-armor","descriprion":"Reduces the power of supereffective attacks taken.","index":232,"generation":"vii"},"hidden":false}],"gender_ratio":{"male":112.5,"female":-12.5},"base_stats":{"hp":97,"attack":107,"defense":101,"special_attack":127,"special_defense":89,"speed":79},"data":{"catch_rate":255,"weight":2300,"height":24,"pokedex_color":"black","is_legendary":true,"is_mythic":false},"evolution_chain":[],"generation":"vii","learned_moves":[{"name":"swords-dance","level":0,"TM":true},{"name":"hyper-beam","level":0,"TM":true},{"name":"solar-beam","level":0,"TM":true},{"name":"thunder-wave","level":0,"TM":true},{"name":"earthquake","level":0,"TM":true},{"name":"toxic","level":0,"TM":true},{"name":"confusion","level":1,"TM":false},{"name":"psychic","level":0,"TM":true},{"name":"double-team","level":0,"TM":true},{"name":"light-screen","level":0,"TM":true},{"name":"reflect","level":0,"TM":true},{"name":"rest","level":0,"TM":true},{"name":"rock-slide","level":0,"TM":true},{"name":"slash","level":7,"TM":false},{"name":"substitute","level":0,"TM":true},{"name":"thief","level":0,"TM":true},{"name":"snore","level":0,"TM":false},{"name":"protect","level":0,"TM":true},{"name":"scary-face","level":0,"TM":true},{"name":"outrage","level":0,"TM":false},{"name":"endure","level":0,"TM":true},{"name":"swagger","level":0,"TM":true},{"name":"sleep-talk","level":0,"TM":true},{"name":"return","level":0,"TM":true},{"name":"frustration","level":0,"TM":true},{"name":"metal-claw","level":1,"TM":false},{"name":"morning-sun","level":1,"TM":false},{"name":"moonlight","level":1,"TM":false},{"name":"hidden-power","level":0,"TM":true},{"name":"future-sight","level":0,"TM":true},{"name":"heat-wave","level":0,"TM":false},{"name":"facade","level":0,"TM":true},{"name":"recycle","level":0,"TM":false},{"name":"brick-break","level":0,"TM":true},{"name":"knock-off","level":0,"TM":false},{"name":"imprison","level":0,"TM":true},{"name":"hyper-voice","level":0,"TM":false},{"name":"rock-tomb","level":0,"TM":true},{"name":"cosmic-power","level":0,"TM":true},{"name":"signal-beam","level":0,"TM":false},{"name":"aerial-ace","level":0,"TM":true},{"name":"iron-defense","level":59,"TM":false},{"name":"calm-mind","level":0,"TM":true},{"name":"dragon-dance","level":0,"TM":true},{"name":"rock-blast","level":19,"TM":false},{"name":"shock-wave","level":0,"TM":false},{"name":"gravity","level":31,"TM":false},{"name":"gyro-ball","level":0,"TM":true},{"name":"embargo","level":0,"TM":true},{"name":"fling","level":0,"TM":true},{"name":"wring-out","level":67,"TM":false},{"name":"magnet-rise","level":0,"TM":false},{"name":"rock-polish","level":0,"TM":true},{"name":"dark-pulse","level":0,"TM":true},{"name":"night-slash","level":23,"TM":false},{"name":"x-scissor","level":0,"TM":true},{"name":"dragon-pulse","level":0,"TM":false},{"name":"power-gem","level":43,"TM":false},{"name":"earth-power","level":0,"TM":false},{"name":"giga-impact","level":0,"TM":true},{"name":"shadow-claw","level":0,"TM":true},{"name":"psycho-cut","level":37,"TM":false},{"name":"mirror-shot","level":1,"TM":false},{"name":"flash-cannon","level":0,"TM":true},{"name":"trick-room","level":0,"TM":true},{"name":"iron-head","level":0,"TM":false},{"name":"stone-edge","level":0,"TM":true},{"name":"stealth-rock","level":53,"TM":false},{"name":"charge-beam","level":1,"TM":false},{"name":"psyshock","level":0,"TM":true},{"name":"autotomize","level":47,"TM":false},{"name":"telekinesis","level":0,"TM":false},{"name":"round","level":0,"TM":true},{"name":"stored-power","level":13,"TM":false},{"name":"ally-switch","level":0,"TM":false},{"name":"bulldoze","level":0,"TM":true},{"name":"confide","level":0,"TM":true},{"name":"smart-strike","level":0,"TM":true},{"name":"brutal-swing","level":0,"TM":true},{"name":"psychic-fangs","level":0,"TM":true},{"name":"prismatic-laser","level":73,"TM":false},{"name":"photon-geyser","level":50,"TM":false},{"name":"breaking-swipe","level":0,"TM":true},{"name":"expanding-force","level":0,"TM":false},{"name":"meteor-beam","level":0,"TM":false}],"sprite":"https://raw.githubusercontent.com/PokeAPI/sprites/master/sprites/pokemon/800.png"}